UniLoaders/__init__.py
UniLoaders/main.py
UniLoaders-0.2.1.dist-info/LICENSE
UniLoaders-0.2.1.dist-info/METADATA
UniLoaders-0.2.1.dist-info/WHEEL
UniLoaders-0.2.1.dist-info/top_level.txt
UniLoaders-0.2.1.dist-info/RECORD
