Metadata-Version: 2.1
Name: UniLoaders
Version: 0.2.1
Summary: Loading everything from URLs to powerpoints
Author: Enzo Bonelli
License: Apache-2.0
Classifier: Programming Language :: Python :: 3
Classifier: License :: OSI Approved :: Apache Software License
Classifier: Operating System :: OS Independent
Requires-Python: >=3.6
License-File: LICENSE
Requires-Dist: langchain
Requires-Dist: unstructured[docx]
Requires-Dist: docx2txt
Requires-Dist: unstructured
Requires-Dist: pdfminer.six
Requires-Dist: pdf2image
Requires-Dist: boto3
